django_wechat_qrcode-1.0.6.dist-info/DESCRIPTION.rst
django_wechat_qrcode-1.0.6.dist-info/METADATA
django_wechat_qrcode-1.0.6.dist-info/RECORD
django_wechat_qrcode-1.0.6.dist-info/WHEEL
django_wechat_qrcode-1.0.6.dist-info/metadata.json
django_wechat_qrcode-1.0.6.dist-info/top_level.txt
qrcode/__init__.py
qrcode/admin.py
qrcode/models.py
qrcode/tests.py
qrcode/urls.py
qrcode/views.py
qrcode/locale/zh_Hans/LC_MESSAGES/django.mo
qrcode/locale/zh_Hans/LC_MESSAGES/django.po
qrcode/templates/qrcode/qrcode.html
wechat_qrcode/__init__.py
wechat_qrcode/admin.py
wechat_qrcode/api.py
wechat_qrcode/models.py
wechat_qrcode/tests.py
wechat_qrcode/urls.py
wechat_qrcode/views.py
wechat_qrcode/locale/zh_Hans/LC_MESSAGES/django.mo
wechat_qrcode/locale/zh_Hans/LC_MESSAGES/django.po
wechat_qrcode/templates/qrcode/qrcode.html
wechat_qrcode/templates/wechat_qrcode/qrcode.html
