Metadata-Version: 2.0
Name: django-wechat-qrcode
Version: 1.0.6
Summary: rename invite count
Home-page: https://github.com/ChanMo/django-wechat-qrcode/
Author: ChanMo
Author-email: chen.orange@aliyun.com
License: BSD License
Keywords: django wechat weixin qrcode
Platform: UNKNOWN
Classifier: Environment :: Web Environment
Classifier: Framework :: Django
Classifier: Intended Audience :: Developers
Classifier: License :: OSI Approved :: BSD License
Classifier: Operating System :: OS Independent
Classifier: Programming Language :: Python
Classifier: Programming Language :: Python :: 3
Classifier: Programming Language :: Python :: 3.2
Classifier: Programming Language :: Python :: 3.3
Classifier: Topic :: Internet :: WWW/HTTP
Classifier: Topic :: Internet :: WWW/HTTP :: Dynamic Content
Requires-Dist: django-wechat-member
Requires-Dist: django-wechat-message
